apscheduler/__init__.py
apscheduler/_context.py
apscheduler/_converters.py
apscheduler/_decorators.py
apscheduler/_enums.py
apscheduler/_events.py
apscheduler/_exceptions.py
apscheduler/_marshalling.py
apscheduler/_retry.py
apscheduler/_structures.py
apscheduler/_utils.py
apscheduler/_validators.py
apscheduler/abc.py
apscheduler/py.typed
apscheduler/_schedulers/__init__.py
apscheduler/_schedulers/async_.py
apscheduler/_schedulers/sync.py
apscheduler/datastores/__init__.py
apscheduler/datastores/base.py
apscheduler/datastores/memory.py
apscheduler/datastores/mongodb.py
apscheduler/datastores/sqlalchemy.py
apscheduler/eventbrokers/__init__.py
apscheduler/eventbrokers/asyncpg.py
apscheduler/eventbrokers/base.py
apscheduler/eventbrokers/local.py
apscheduler/eventbrokers/mqtt.py
apscheduler/eventbrokers/psycopg.py
apscheduler/eventbrokers/redis.py
apscheduler/executors/__init__.py
apscheduler/executors/async_.py
apscheduler/executors/qt.py
apscheduler/executors/subprocess.py
apscheduler/executors/thread.py
apscheduler/serializers/__init__.py
apscheduler/serializers/cbor.py
apscheduler/serializers/json.py
apscheduler/serializers/pickle.py
apscheduler/triggers/__init__.py
apscheduler/triggers/calendarinterval.py
apscheduler/triggers/combining.py
apscheduler/triggers/date.py
apscheduler/triggers/interval.py
apscheduler/triggers/cron/__init__.py
apscheduler/triggers/cron/expressions.py
apscheduler/triggers/cron/fields.py
dd_apscheduler-1.0.0.dist-info/licenses/LICENSE.txt
dd_apscheduler-1.0.0.dist-info/METADATA
dd_apscheduler-1.0.0.dist-info/WHEEL
dd_apscheduler-1.0.0.dist-info/top_level.txt
dd_apscheduler-1.0.0.dist-info/RECORD
