Metadata-Version: 2.4
Name: dd-apscheduler
Version: 1.0.0
Summary: In-process task scheduler with Cron-like capabilities - Fork with critical stability and database handling fixes
Author-email: Dynamic Deploy <dynamicdeploy@gmail.com>
License-Expression: MIT
Project-URL: Documentation, https://apscheduler.readthedocs.io/en/master/
Project-URL: Changelog, https://apscheduler.readthedocs.io/en/master/versionhistory.html
Project-URL: Source code, https://github.com/dynamicdeploy/apscheduler
Project-URL: Issue tracker, https://github.com/dynamicdeploy/apscheduler/issues
Keywords: scheduling,cron
Classifier: Development Status :: 5 - Production/Stable
Classifier: Intended Audience :: Developers
Classifier: Framework :: AnyIO
Classifier: Typing :: Typed
Classifier: Programming Language :: Python
Classifier: Programming Language :: Python :: 3 :: Only
Classifier: Programming Language :: Python :: 3.10
Classifier: Programming Language :: Python :: 3.11
Classifier: Programming Language :: Python :: 3.12
Classifier: Programming Language :: Python :: 3.13
Classifier: Programming Language :: Python :: 3.14
Requires-Python: >=3.10
License-File: LICENSE.txt
Requires-Dist: anyio~=4.0
Requires-Dist: attrs>=22.1
Requires-Dist: tenacity<10.0,>=8.0
Requires-Dist: tzlocal>=3.0
Requires-Dist: typing_extensions>=4.0; python_version < "3.11"
Provides-Extra: asyncpg
Requires-Dist: asyncpg>=0.20; extra == "asyncpg"
Provides-Extra: cbor
Requires-Dist: cbor2>=5.0; extra == "cbor"
Provides-Extra: mongodb
Requires-Dist: pymongo>=4.13.0; extra == "mongodb"
Provides-Extra: mqtt
Requires-Dist: paho-mqtt>=2.0; extra == "mqtt"
Provides-Extra: redis
Requires-Dist: redis>=5.0.1; extra == "redis"
Provides-Extra: sqlalchemy
Requires-Dist: sqlalchemy[asyncio]>=2.0.24; extra == "sqlalchemy"
Dynamic: license-file
